{
  "$schema": "https://mintlify.com/docs.json",
  "theme": "mint",
  "name": "Fatorly",
  "colors": { "primary": "#0d9488", "light": "#2dd4bf", "dark": "#0d9488" },
  "favicon": "/images/favicon.png",
  "logo": {
    "light": "/logo/fatorly-light.svg",
    "dark": "/logo/fatorly-dark.svg"
  },
  "navigation": {
    "languages": [
      {
        "language": "en",
        "default": true,
        "groups": [
          { "group": "Getting Started", "pages": [
            "en/index",
            "en/getting-started/register",
            "en/getting-started/login",
            "en/getting-started/forgot-password",
            "en/getting-started/reset-password",
            "en/getting-started/verify-email",
            "en/getting-started/onboarding",
            "en/getting-started/mfa-setup"
          ]},
          { "group": "Dashboard", "pages": [
            "en/home/dashboard"
          ]},
          { "group": "Sales", "pages": [
            "en/sales/sales-invoices",
            "en/sales/sales-credit-notes"
          ]},
          { "group": "Purchases", "pages": [
            "en/purchases/purchase-invoices",
            "en/purchases/purchase-credit-notes"
          ]},
          { "group": "Self-Billing", "pages": [
            "en/self-billing/self-billing"
          ]},
          { "group": "The Invoice Editor", "pages": [
            "en/invoicing/create-invoice",
            "en/invoicing/invoice-field-reference",
            "en/invoicing/view-invoice"
          ]},
          { "group": "Reports", "pages": [
            "en/reports/overview",
            "en/reports/running-a-report",
            "en/reports/downloads",
            "en/reports/scheduled-reports",
            "en/reports/submission-failures"
          ]},
          { "group": "Master Data", "pages": [
            "en/master-data/items",
            "en/master-data/customers",
            "en/master-data/vendors",
            "en/master-data/payment-methods",
            "en/files/files-library"
          ]},
          { "group": "Company Settings", "pages": [
            "en/settings/company-profile",
            "en/settings/branding-documents",
            "en/settings/company-configuration",
            "en/settings/number-series",
            "en/settings/team-auditors",
            "en/settings/usage",
            "en/settings/support-access",
            "en/settings/linking-companies",
            "en/settings/leave-fatorly",
            "en/settings/integrations",
            "en/settings/api-keys"
          ]},
          { "group": "Account", "pages": [
            "en/account/profile",
            "en/settings/change-password",
            "en/home/whats-new"
          ]},
          { "group": "Multi-Company", "pages": [
            "en/multi-company/switching-companies"
          ]},
          { "group": "Auditor", "pages": [
            "en/auditor/company-selector",
            "en/auditor/auditing-a-company"
          ]},
          { "group": "Developers", "pages": [
            "en/developers/overview",
            "en/developers/authentication",
            "en/developers/quickstart",
            "en/developers/idempotency",
            "en/developers/errors",
            "en/developers/api-reference"
          ]},
          { "group": "API Reference", "openapi": "api-reference/openapi.json" }
        ]
      },
      {
        "language": "ar",
        "groups": [
          { "group": "ابدأ من هنا", "pages": [
            "ar/index",
            "ar/getting-started/register",
            "ar/getting-started/login",
            "ar/getting-started/forgot-password",
            "ar/getting-started/reset-password",
            "ar/getting-started/verify-email",
            "ar/getting-started/onboarding",
            "ar/getting-started/mfa-setup"
          ]},
          { "group": "الرئيسية", "pages": [
            "ar/home/dashboard"
          ]},
          { "group": "المبيعات", "pages": [
            "ar/sales/sales-invoices",
            "ar/sales/sales-credit-notes"
          ]},
          { "group": "المشتريات", "pages": [
            "ar/purchases/purchase-invoices",
            "ar/purchases/purchase-credit-notes"
          ]},
          { "group": "الفوترة الذاتية", "pages": [
            "ar/self-billing/self-billing"
          ]},
          { "group": "محرّر الفواتير", "pages": [
            "ar/invoicing/create-invoice",
            "ar/invoicing/invoice-field-reference",
            "ar/invoicing/view-invoice"
          ]},
          { "group": "التقارير", "pages": [
            "ar/reports/overview",
            "ar/reports/running-a-report",
            "ar/reports/downloads",
            "ar/reports/scheduled-reports",
            "ar/reports/submission-failures"
          ]},
          { "group": "البيانات الأساسية", "pages": [
            "ar/master-data/items",
            "ar/master-data/customers",
            "ar/master-data/vendors",
            "ar/master-data/payment-methods",
            "ar/files/files-library"
          ]},
          { "group": "إعدادات الشركة", "pages": [
            "ar/settings/company-profile",
            "ar/settings/branding-documents",
            "ar/settings/company-configuration",
            "ar/settings/number-series",
            "ar/settings/team-auditors",
            "ar/settings/usage",
            "ar/settings/support-access",
            "ar/settings/linking-companies",
            "ar/settings/leave-fatorly",
            "ar/settings/integrations",
            "ar/settings/api-keys"
          ]},
          { "group": "الحساب", "pages": [
            "ar/account/profile",
            "ar/settings/change-password",
            "ar/home/whats-new"
          ]},
          { "group": "تعدّد الشركات", "pages": [
            "ar/multi-company/switching-companies"
          ]},
          { "group": "المدقق", "pages": [
            "ar/auditor/company-selector",
            "ar/auditor/auditing-a-company"
          ]},
          { "group": "المطوّرون", "pages": [
            "ar/developers/overview",
            "ar/developers/authentication",
            "ar/developers/quickstart",
            "ar/developers/idempotency",
            "ar/developers/errors",
            "ar/developers/api-reference"
          ]},
          { "group": "API Reference", "openapi": "api-reference/openapi.json" }
        ]
      }
    ]
  }
}
